{
    "name": "filesA",
    "version": "0.0.1",
    "description": "Proves File system",
    "files": [
        "README.md",
        "enums.d.ts",
        "shims.d.ts",
        "filesA.cpp",
        "filesA.ts"
    ],
    "testFiles": [
        "tests.ts"
    ],
    "public": true,
    "targetVersion": "0.11.9",
    "dependencies": {
        "core": "*"
    },
    "yotta": {
        "config": {
            "microbit-dal": {
                "interface": {
                    "fs": 1
                }
            }
        }
    },
    "installedVersion": "file:../pxt-filesystem"
}
